ragtrace_lite/__init__.py
ragtrace_lite/cli.py
ragtrace_lite/config_loader.py
ragtrace_lite/data_processor.py
ragtrace_lite/db_manager.py
ragtrace_lite/evaluator.py
ragtrace_lite/hcx_proxy.py
ragtrace_lite/hcx_ragas_adapter.py
ragtrace_lite/llm_factory.py
ragtrace_lite/logging_system.py
ragtrace_lite/main.py
ragtrace_lite/py.typed
ragtrace_lite/report_generator.py
ragtrace_lite/web_dashboard.py
ragtrace_lite-1.0.7.dist-info/licenses/LICENSE
ragtrace_lite-1.0.7.dist-info/METADATA
ragtrace_lite-1.0.7.dist-info/WHEEL
ragtrace_lite-1.0.7.dist-info/entry_points.txt
ragtrace_lite-1.0.7.dist-info/top_level.txt
ragtrace_lite-1.0.7.dist-info/RECORD
