Metadata-Version: 2.4
Name: ragtrace-lite
Version: 1.0.7
Summary: Lightweight RAG evaluation framework with Korean language support, BGE-M3 embeddings, and HCX-005/Gemini LLMs
Author-email: RAGTrace Lite Contributors <ntts9990@gmail.com>
Maintainer-email: RAGTrace Lite Contributors <ntts9990@gmail.com>
License: Apache-2.0
Project-URL: Homepage, https://github.com/ntts9990/ragtrace-lite
Project-URL: Documentation, https://ragtrace-lite.readthedocs.io
Project-URL: Repository, https://github.com/ntts9990/ragtrace-lite
Project-URL: Issues, https://github.com/ntts9990/ragtrace-lite/issues
Project-URL: Changelog, https://github.com/ntts9990/ragtrace-lite/blob/main/CHANGELOG.md
Keywords: rag,evaluation,llm,ai,ragas,korean,hcx,gemini
Classifier: Development Status :: 4 - Beta
Classifier: Intended Audience :: Developers
Classifier: Intended Audience :: Science/Research
Classifier: License :: OSI Approved :: Apache Software License
Classifier: Operating System :: OS Independent
Classifier: Programming Language :: Python :: 3
Classifier: Programming Language :: Python :: 3.9
Classifier: Programming Language :: Python :: 3.10
Classifier: Programming Language :: Python :: 3.11
Classifier: Programming Language :: Python :: 3.12
Classifier: Topic :: Scientific/Engineering :: Artificial Intelligence
Classifier: Topic :: Software Development :: Libraries :: Python Modules
Requires-Python: >=3.9
License-File: LICENSE
Requires-Dist: ragas>=0.1.0
Requires-Dist: pydantic>=2.0.0
Requires-Dist: pydantic-settings>=2.0.0
Requires-Dist: pandas>=2.0.0
Requires-Dist: numpy>=1.24.0
Requires-Dist: requests>=2.31.0
Requires-Dist: pyyaml>=6.0
Requires-Dist: datasets>=2.14.0
Requires-Dist: python-dotenv>=1.0.0
Requires-Dist: tqdm>=4.65.0
Requires-Dist: tenacity>=8.0.0
Requires-Dist: openpyxl>=3.1.0
Requires-Dist: jinja2>=3.1.6
Provides-Extra: llm
Requires-Dist: google-generativeai>=0.3.0; extra == "llm"
Requires-Dist: langchain>=0.0.300; extra == "llm"
Requires-Dist: langchain-community>=0.0.10; extra == "llm"
Provides-Extra: embeddings
Requires-Dist: sentence-transformers>=2.2.2; extra == "embeddings"
Requires-Dist: torch>=2.0.0; extra == "embeddings"
Requires-Dist: huggingface-hub>=0.17.0; extra == "embeddings"
Requires-Dist: langchain-huggingface>=0.0.1; extra == "embeddings"
Provides-Extra: enhanced
Requires-Dist: plotly>=5.17.0; extra == "enhanced"
Requires-Dist: psutil>=5.9.0; extra == "enhanced"
Requires-Dist: scipy>=1.10.0; extra == "enhanced"
Requires-Dist: scikit-learn>=1.2.0; extra == "enhanced"
Provides-Extra: dev
Requires-Dist: pytest>=7.0.0; extra == "dev"
Requires-Dist: pytest-cov>=4.0.0; extra == "dev"
Requires-Dist: black>=22.0.0; extra == "dev"
Requires-Dist: flake8>=4.0.0; extra == "dev"
Requires-Dist: mypy>=0.950; extra == "dev"
Requires-Dist: isort>=5.10.0; extra == "dev"
Provides-Extra: all
Requires-Dist: ragtrace-lite[embeddings,enhanced,llm]; extra == "all"
Dynamic: license-file
